gitscrum/__init__.py
gitscrum/retro.py
gitscrum/standup.py
gitscrum/utils/base.py
gitscrum/utils/warn.py
gitscrum-0.0.1.dist-info/entry_points.txt
gitscrum-0.0.1.dist-info/LICENSE
gitscrum-0.0.1.dist-info/WHEEL
gitscrum-0.0.1.dist-info/METADATA
gitscrum-0.0.1.dist-info/RECORD
