Metadata-Version: 2.1
Name: gitscrum
Version: 0.0.1
Summary: A CLI for scrum tasks with git
Home-page: https://github.com/ConorSheehan1/gitscrum
License: MIT
Author: Conor Sheehan
Author-email: conor.sheehan.dev@gmail.com
Requires-Python: >=3.6,<4.0
Classifier: Intended Audience :: Developers
Classifier: License :: OSI Approved :: MIT License
Classifier: Programming Language :: Python :: 3
Classifier: Programming Language :: Python :: 3.6
Classifier: Programming Language :: Python :: 3.7
Classifier: Programming Language :: Python :: 3.8
Classifier: Topic :: Software Development
Classifier: Topic :: Utilities
Requires-Dist: fire (>=0.3.1,<0.4.0)
Requires-Dist: termcolor (>=1.1.0,<2.0.0)
Requires-Dist: terminaltables (>=3.1.0,<4.0.0)
